plain/loginlink/CHANGELOG.md
plain/loginlink/README.md
plain/loginlink/__init__.py
plain/loginlink/forms.py
plain/loginlink/links.py
plain/loginlink/signing.py
plain/loginlink/urls.py
plain/loginlink/views.py
plain/loginlink/templates/email/loginlink.html
plain/loginlink/templates/email/loginlink.subject.txt
plain/loginlink/templates/loginlink/failed.html
plain/loginlink/templates/loginlink/sent.html
plain_loginlink-0.16.0.dist-info/METADATA
plain_loginlink-0.16.0.dist-info/WHEEL
plain_loginlink-0.16.0.dist-info/licenses/LICENSE
plain_loginlink-0.16.0.dist-info/RECORD
