Metadata-Version: 2.4
Name: plain.loginlink
Version: 0.16.0
Summary: Link-based authentication for Plain.
Author-email: Dave Gaeddert <dave.gaeddert@dropseed.dev>
License-Expression: BSD-3-Clause
License-File: LICENSE
Requires-Python: >=3.13
Requires-Dist: plain-email<1.0.0
Requires-Dist: plain<1.0.0
